particle/__init__.py
particle/particle.py
python3_particle-0.1.dist-info/LICENSE
python3_particle-0.1.dist-info/METADATA
python3_particle-0.1.dist-info/WHEEL
python3_particle-0.1.dist-info/top_level.txt
python3_particle-0.1.dist-info/RECORD
