Metadata-Version: 2.1
Name: python3-particle
Version: 0.1
Summary: A Python wrapper around the Particle (particle.io) Cloud API
Home-page: https://github.com/DarkSector/python-particle
Author: Pronoy Chopra
Author-email: contact@pronoy.in
License: MIT License
Platform: UNKNOWN
Classifier: Development Status :: 2 - Pre-Alpha
Classifier: Environment :: Web Environment
Classifier: Intended Audience :: Developers
Classifier: Intended Audience :: Science/Research
Classifier: Intended Audience :: Information Technology
Classifier: License :: OSI Approved :: MIT License
Classifier: Operating System :: OS Independent
Classifier: Programming Language :: Python
Classifier: Programming Language :: Python :: 3.6
Classifier: Topic :: Internet :: WWW/HTTP
Classifier: Topic :: Internet :: WWW/HTTP :: Dynamic Content
Requires-Dist: python-dateutil (==2.8.1)
Requires-Dist: pytz (==2019.3)
Requires-Dist: requests (==2.7.0)
Requires-Dist: pexpect (==3.3)
